shcli/__init__.py
shcli/api.py
shcli/cli.py
tests/api/__init__.py
tests/api/test_create.py
tests/cli/__init__.py
tests/cli/test_create.py
shcli-0.2.0.dist-info/LICENSE.txt
shcli-0.2.0.dist-info/METADATA
shcli-0.2.0.dist-info/WHEEL
shcli-0.2.0.dist-info/entry_points.txt
shcli-0.2.0.dist-info/top_level.txt
shcli-0.2.0.dist-info/RECORD
