Metadata-Version: 2.1
Name: shcli
Version: 0.2.0
Summary: Python client for Socialhome.
Home-page: https://git.feneas.org/socialhome/shcli
Author: Jason Robinson
Author-email: mail@jasonrobinson.me
Maintainer: Jason Robinson
Maintainer-email: mail@jasonrobinson.me
License: MIT
Download-URL: https://git.feneas.org/socialhome/shcli/-/releases
Keywords: socialhome federation
Platform: UNKNOWN
Classifier: Development Status :: 3 - Alpha
Classifier: Environment :: Console
Classifier: Intended Audience :: Developers
Classifier: Intended Audience :: End Users/Desktop
Classifier: License :: OSI Approved :: MIT License
Classifier: Programming Language :: Python
Classifier: Programming Language :: Python :: 3 :: Only
Classifier: Programming Language :: Python :: 3.6
Classifier: Programming Language :: Python :: 3.7
Classifier: Programming Language :: Python :: Implementation :: CPython
Classifier: Topic :: Communications
Classifier: Topic :: Internet
Classifier: Topic :: Software Development :: Libraries :: Python Modules
Classifier: Topic :: Utilities
Requires-Python: >=3.6
Requires-Dist: requests (>=2.8.0)
Requires-Dist: click (>=6)
